hyperion/__init__.py
hyperion/__main__.py
hyperion/util.py
hyperion/api/__init__.py
hyperion/api/bike.py
hyperion/api/crime.py
hyperion/api/geo.py
hyperion/api/social.py
hyperion/api/util.py
hyperion/cli/__init__.py
hyperion/cli/getters.py
hyperion/cli/serializers.py
hyperion/cli/util.py
hyperion/fetch/__init__.py
hyperion/fetch/bikeregister.py
hyperion/fetch/police.py
hyperion/fetch/postcode.py
hyperion/fetch/twitter.py
hyperion/fetch/wikipedia.py
hyperion/models/__init__.py
hyperion/models/base.py
hyperion/models/bike.py
hyperion/models/neighbourhood.py
hyperion/models/postcode.py
hyperion/models/util.py
hyperion/store/__init__.py
hyperion/test/__init__.py
hyperion/test/test_fetch.py
hyperion_cli-1.0.1.dist-info/METADATA
hyperion_cli-1.0.1.dist-info/RECORD
hyperion_cli-1.0.1.dist-info/WHEEL
hyperion_cli-1.0.1.dist-info/entry_points.txt
hyperion_cli-1.0.1.dist-info/top_level.txt
test/__init__.py
test/test_api.py
test/test_cli.py
test/test_fetch.py
test/util.py
