Metadata-Version: 2.1
Name: hyperion-cli
Version: 1.0.1
Summary: CLI and rest api for postcode data
Home-page: https://github.com/arlyon/hyperion
Author: arlyon
Author-email: arlyon@me.com
License: MIT
Platform: UNKNOWN
Requires-Dist: Click
Requires-Dist: aiohttp
Requires-Dist: aiohttp-cors
Requires-Dist: colorama
Requires-Dist: uvloop
Requires-Dist: peewee
Requires-Dist: geopy
Requires-Dist: lxml
Requires-Dist: feedparser
Requires-Dist: brotlipy
Requires-Dist: aiobreaker
